page_objects/__init__.py
page_objects/page_objects.py
page_objects/select.py
page_objects/wait.py
selenium_page_objects-0.2.1.dist-info/LICENSE
selenium_page_objects-0.2.1.dist-info/METADATA
selenium_page_objects-0.2.1.dist-info/WHEEL
selenium_page_objects-0.2.1.dist-info/top_level.txt
selenium_page_objects-0.2.1.dist-info/RECORD
